# Lab 2: Java Compilation → Bytecode → Execution Pipeline (with JIT Demo)

## Objective

Practice the complete Java execution workflow:

* Write Java source code
* Compile source code into bytecode
* Inspect generated bytecode
* Execute bytecode on the JVM
* Observe Just-In-Time (JIT) compilation and performance optimization

---

## Step 1 — Write a Simple Program

### Where to Start

Create a file named `Calculation.java`.

```java
public class Calculation {
    public static void main(String[] args) {
        int result = 25 * 4;
        System.out.println(result);
    }
}
```

### Why?

This is a simple program that demonstrates the complete Java compile-and-run cycle.

---

## Step 2 — Compile the Program

### What to Do

```bash
javac Calculation.java
```

### Why?

The Java compiler (`javac`) converts source code into platform-independent bytecode.

Generated file:

```text
Calculation.class
```

---

## Step 3 — Run the Program

### What to Do

```bash
java Calculation
```

### Expected Output

```text
100
```

### Why?

The JVM loads and executes the bytecode stored in `Calculation.class`.

---

## Step 4 — Inspect the Bytecode

### What to Do

```bash
javap -c Calculation
```

### Sample Output

```text
Compiled from "Calculation.java"
public class Calculation {
  public Calculation();
    Code:
       0: aload_0
       1: invokespecial #1
       4: return

  public static void main(java.lang.String[]);
    Code:
       0: bipush        100
       2: istore_1
       3: getstatic     #2
       6: iload_1
       7: invokevirtual #3
      10: return
}
```

### Why?

`javap -c` disassembles the `.class` file and displays the JVM bytecode instructions executed by the JVM or optimized by the JIT compiler.

---

# Understanding the Java Execution Pipeline

```text
Calculation.java
        │
        ▼
     javac
        │
        ▼
Calculation.class
(Bytecode)
        │
        ▼
      JVM
        │
        ├── Interpreter
        │
        └── JIT Compiler
                │
                ▼
        Native Machine Code
                │
                ▼
            CPU Executes
```

---

## Step 5 — Create a Micro-Benchmark for JIT

### Where to Start

Create a file named `JITHint.java`.

```java
public class JITHint {
    public static void main(String[] args) {
        long sum = 0;

        for (int r = 0; r < 5; r++) {

            long start = System.nanoTime();

            for (int i = 0; i < 50_000_000; i++) {
                sum += i;
            }

            long end = System.nanoTime();

            System.out.println(
                "Run " + r +
                " took " +
                (end - start) / 1_000_000 +
                " ms"
            );
        }

        System.out.println(sum);
    }
}
```

### Why?

The repeated loop becomes a **hot method**. The JVM identifies frequently executed code and compiles it into optimized native machine code using the JIT compiler.

---

## Step 6 — Compare Interpreter vs JIT

### Compile

```bash
javac JITHint.java
```

### Run Using Interpreter Only

```bash
java -Xint JITHint
```

### Run Using Default JVM (JIT Enabled)

```bash
java JITHint
```

### Why?

#### `-Xint`

* Disables JIT compilation
* JVM executes bytecode instruction-by-instruction
* Slower execution

#### Default JVM

* Starts with interpretation
* Detects hot code paths
* Compiles them to native machine code
* Faster execution

### Example Output

```text
Interpreter (-Xint)

Run 0 took 1800 ms
Run 1 took 1790 ms
Run 2 took 1802 ms
Run 3 took 1795 ms
Run 4 took 1801 ms
```

```text
Default JVM (JIT)

Run 0 took 320 ms
Run 1 took 180 ms
Run 2 took 110 ms
Run 3 took 95 ms
Run 4 took 92 ms
```

Notice how later runs become faster after JIT optimization occurs.

---

## Step 7 — Force Aggressive Compilation

### What to Do

```bash
java -Xcomp JITHint
```

### Why?

`-Xcomp` forces methods to be compiled before execution.

Useful for:

* Studying JIT behavior
* Benchmarking
* JVM experimentation

### Notes

| Option   | Description                     |
| -------- | ------------------------------- |
| `-Xint`  | Interpreter only                |
| Default  | Interpreter + JIT               |
| `-Xcomp` | Compile everything aggressively |

---

# Understanding JIT Compilation

## Without JIT

```text
Bytecode
   │
   ▼
Interpreter
   │
   ▼
CPU
```

Every instruction is interpreted repeatedly.

---

## With JIT

```text
Bytecode
   │
   ▼
Interpreter
   │
   ▼
Hot Code Detected
   │
   ▼
JIT Compiler
   │
   ▼
Native Machine Code
   │
   ▼
CPU
```

Frequently executed code runs significantly faster.

---

# Learning Outcomes

By completing this lab, you learned how to:

* Compile Java source code using `javac`
* Generate JVM bytecode (`.class` files)
* Execute bytecode using the JVM
* Inspect bytecode using `javap`
* Understand the Java execution pipeline
* Observe JIT compilation in action
* Compare interpreter-only execution with JIT-optimized execution
* Experiment with JVM performance options (`-Xint`, default JIT, and `-Xcomp`)

---

# Conclusion

Java achieves platform independence through bytecode while maintaining high performance through JIT compilation. In this lab, you experienced the complete journey from source code to bytecode to optimized native machine code execution.
